[{"BayerFlamsteed":"6Bet Ari","Mag":"2.64","Spectrum":"A5V...","ColorIndex":"0.165","X":"14.98444","Y":"8.19007","Z":"6.48963"},{"BayerFlamsteed":"8Iot Ari","Mag":"5.09","Spectrum":"K1p...","ColorIndex":"0.921","X":"167.66356","Y":"94.23328","Z":"61.81567"},{"BayerFlamsteed":"9Lam Ari","Mag":"4.79","Spectrum":"F0V","ColorIndex":"0.290","X":"32.57345","Y":"18.41596","Z":"16.34489"},{"BayerFlamsteed":"12Kap Ari","Mag":"5.03","Spectrum":"A2m","ColorIndex":"0.121","X":"45.15502","Y":"27.82444","Z":"22.13075"},{"BayerFlamsteed":"13Alp Ari","Mag":"2.01","Spectrum":"K2III","ColorIndex":"1.151","X":"15.75753","Y":"9.76736","Z":"8.04675"},{"BayerFlamsteed":"17Eta Ari","Mag":"5.23","Spectrum":"F5V","ColorIndex":"0.457","X":"23.5034","Y":"15.38015","Z":"10.90097"},{"BayerFlamsteed":"22The Ari","Mag":"5.58","Spectrum":"A1Vn","ColorIndex":"0.011","X":"91.99738","Y":"63.30241","Z":"40.42738"},{"BayerFlamsteed":"37Omi Ari","Mag":"5.78","Spectrum":"B9Vn","ColorIndex":"-0.024","X":"107.45562","Y":"93.86304","Z":"39.0641"},{"BayerFlamsteed":"43Sig Ari","Mag":"5.52","Spectrum":"B7V","ColorIndex":"-0.099","X":"104.06132","Y":"96.60907","Z":"38.26519"},{"BayerFlamsteed":"48Eps Ari","Mag":"4.63","Spectrum":"A2Vs","ColorIndex":"0.048","X":"59.27208","Y":"58.866","Z":"32.63756"},{"BayerFlamsteed":"57Del Ari","Mag":"4.35","Spectrum":"K2IIIvar","ColorIndex":"1.033","X":"32.45867","Y":"35.9315","Z":"17.36285"},{"BayerFlamsteed":"58Zet Ari","Mag":"4.87","Spectrum":"A1V","ColorIndex":"-0.007","X":"64.19899","Y":"73.14175","Z":"37.44473"}]